py_git_auto_version-1.2.0.dist-info/METADATA
py_git_auto_version-1.2.0.dist-info/WHEEL
py_git_auto_version-1.2.0.dist-info/entry_points.txt
py_git_auto_version-1.2.0.dist-info/licenses/LICENSE
py_git_auto_version/__init__.py
py_git_auto_version/_version.py
py_git_auto_version/cli.py
py_git_auto_version/extractors/__init__.py
py_git_auto_version/extractors/abc/__init__.py
py_git_auto_version/extractors/abc/version_extractor_base.py
py_git_auto_version/extractors/mixed_extractor.py
py_git_auto_version/extractors/parser_extractor.py
py_git_auto_version/extractors/pattern_extractor.py
py_git_auto_version/generators/__init__.py
py_git_auto_version/generators/abc/__init__.py
py_git_auto_version/generators/abc/basic_version_generator.py
py_git_auto_version/generators/version_generator_adds_branch_as_local.py
py_git_auto_version/git.py
py_git_auto_version/git_ref.py
py_git_auto_version/re_compile_func.py
py_git_auto_version/settings/__init__.py
py_git_auto_version/settings/auto_version.py
py_git_auto_version/settings/github.py
py_git_auto_version/typing/__init__.py
py_git_auto_version-1.2.0.dist-info/RECORD
